[
    {
      "model": "liquidaciones.nomina",
      "pk": 1,
      "fields": {
        "empresa": "1",
        "periodo": 202202,
        "no_personal": 3800002,
        "apellido_nombre": "TENORIO ANDRES",
        "nombre_completo": "Tenorio Andres",
        "NIF": "",
        "divp": "COBO",
        "division_persona": "Bogotá",
        "percalnom": "CO",
        "area_nomina": "Globant CO Mensuales",
        "paper": "01",
        "denom_periodos": "Mensual" ,
        "periodo_inicia":202207,
        "fecha_inicia": "2022-07-31",
        "tpclcnom": "", 
        "idnom": "",
        "area_cal_nom" : "CO",
        "area_nomina2" : "Globant CO Mensuales",
        "paper2" : "01",
        "denom_periodos2": "Mensual",
        "periodo_fin": 202207,
        "fecha_fin" : "2022-07-31",
        "tpclcnom2" : "",
        "idnom2": "",
        "ag_pai": "38", 
        "cod_concepto": 1,
        "desc_concepto" : "Seguro de Vida",
        "cantidad" : 0,
        "importe" : 7000, 
        "moneda": "COP"
      }
    },
     {
        "model": "liquidaciones.nomina",
        "pk": 2,
        "fields": {
          "empresa": "1",
          "periodo": 202201,
          "no_personal": 3800002,
          "apellido_nombre": "TENORIO ANDRES",
          "nombre_completo": "Tenorio Andres",
          "NIF": "",
          "divp": "COBO",
          "division_persona": "Bogotá",
          "percalnom": "CO",
          "area_nomina": "Globant CO Mensuales",
          "paper": "01",
          "denom_periodos": "Mensual" ,
          "periodo_inicia":202207,
          "fecha_inicia": "2022-07-31",
          "tpclcnom": "", 
          "idnom": "",
          "area_cal_nom" : "CO",
          "area_nomina2" : "Globant CO Mensuales",
          "paper2" : "01",
          "denom_periodos2": "Mensual",
          "periodo_fin": 202207,
          "fecha_fin" : "2022-07-31",
          "tpclcnom2" : "",
          "idnom2": "",
          "ag_pai": "38", 
          "cod_concepto": 1,
          "desc_concepto" : "Descuento ESPP",
          "cantidad" : 5,
          "importe" : 1629056.9, 
          "moneda": "COP"
        }
    }
  ]